invenio_csl_rest/__init__.py
invenio_csl_rest/ext.py
invenio_csl_rest/version.py
invenio_csl_rest/views.py
invenio_csl_rest-1.0.0a1.dist-info/top_level.txt
invenio_csl_rest-1.0.0a1.dist-info/entry_points.txt
invenio_csl_rest-1.0.0a1.dist-info/METADATA
invenio_csl_rest-1.0.0a1.dist-info/DESCRIPTION.rst
invenio_csl_rest-1.0.0a1.dist-info/metadata.json
invenio_csl_rest-1.0.0a1.dist-info/WHEEL
invenio_csl_rest-1.0.0a1.dist-info/RECORD
